[
  {
    "city": "Aloxe-Corton",
    "start": "2025-06-01T13:34",
    "end": "2025-06-01T13:35",
    "duration_h": 0,
    "lat": 47.0447,
    "lon": 4.83901
  },
  {
    "city": "Ancy-le-Libre",
    "start": "2025-05-29T17:13",
    "end": "2025-07-17T18:09",
    "duration_h": 1177,
    "lat": 47.63511,
    "lon": 4.19506
  },
  {
    "city": "Asnelles",
    "start": "2025-05-01T19:35",
    "end": "2025-05-01T19:35",
    "duration_h": 0,
    "lat": 48.8761,
    "lon": 2.32496
  },
  {
    "city": "Beaune",
    "start": "2025-06-01T16:26",
    "end": "2025-06-01T16:26",
    "duration_h": 0,
    "lat": 46.90749,
    "lon": 4.74978
  },
  {
    "city": "Benoisey",
    "start": "2025-05-30T12:43",
    "end": "2025-05-30T12:43",
    "duration_h": 0,
    "lat": 47.55567,
    "lon": 4.42353
  },
  {
    "city": "Bréhal",
    "start": "2025-05-04T15:56",
    "end": "2025-05-04T15:57",
    "duration_h": 0,
    "lat": 48.83991,
    "lon": 2.31941
  },
  {
    "city": "Bricqueville-sur-Mer",
    "start": "2025-05-04T15:44",
    "end": "2025-05-04T15:45",
    "duration_h": 0,
    "lat": 48.83991,
    "lon": 2.31941
  },
  {
    "city": "Brochon",
    "start": "2025-05-31T18:54",
    "end": "2025-05-31T18:54",
    "duration_h": 0,
    "lat": 47.23255,
    "lon": 4.90452
  },
  {
    "city": "Chambœuf",
    "start": "2025-05-31T20:08",
    "end": "2025-06-01T10:12",
    "duration_h": 14,
    "lat": 47.2326,
    "lon": 4.90478
  },
  {
    "city": "Chambolle-Musigny",
    "start": "2025-06-01T12:04",
    "end": "2025-06-01T12:04",
    "duration_h": 0,
    "lat": 47.15282,
    "lon": 4.94912
  },
  {
    "city": "Chassagne-Montrachet",
    "start": "2025-06-01T17:33",
    "end": "2025-06-01T17:33",
    "duration_h": 0,
    "lat": 46.90749,
    "lon": 4.74978
  },
  {
    "city": "Chassey",
    "start": "2025-05-30T13:40",
    "end": "2025-05-30T13:40",
    "duration_h": 0,
    "lat": 47.4437,
    "lon": 4.41392
  },
  {
    "city": "Chassignelles",
    "start": "2025-05-29T18:13",
    "end": "2025-05-29T18:13",
    "duration_h": 0,
    "lat": 47.7247,
    "lon": 4.22364
  },
  {
    "city": "Chenôve",
    "start": "2025-05-31T17:38",
    "end": "2025-05-31T17:38",
    "duration_h": 0,
    "lat": 47.23255,
    "lon": 4.90452
  },
  {
    "city": "Clamerey",
    "start": "2025-05-30T14:40",
    "end": "2025-05-30T17:52",
    "duration_h": 3,
    "lat": 47.29827,
    "lon": 4.519
  },
  {
    "city": "Créancey",
    "start": "2025-05-31T10:47",
    "end": "2025-05-31T10:47",
    "duration_h": 0,
    "lat": 47.18874,
    "lon": 4.66825
  },
  {
    "city": "Crugey",
    "start": "2025-05-31T11:37",
    "end": "2025-05-31T11:37",
    "duration_h": 0,
    "lat": 47.23386,
    "lon": 4.74474
  },
  {
    "city": "Cry",
    "start": "2025-05-29T19:03",
    "end": "2025-05-29T19:03",
    "duration_h": 0,
    "lat": 47.64024,
    "lon": 4.29524
  },
  {
    "city": "Curley",
    "start": "2025-05-31T19:58",
    "end": "2025-07-17T18:05",
    "duration_h": 1126,
    "lat": 47.17998,
    "lon": 4.88908
  },
  {
    "city": "Dijon",
    "start": "2025-05-31T14:21",
    "end": "2025-05-31T17:15",
    "duration_h": 3,
    "lat": 47.22914,
    "lon": 4.91317
  },
  {
    "city": "Englesqueville-la-Percée",
    "start": "2025-05-02T16:17",
    "end": "2025-05-02T16:19",
    "duration_h": 0,
    "lat": 49.34439,
    "lon": -1.09021
  },
  {
    "city": "Fixin",
    "start": "2025-05-31T18:02",
    "end": "2025-05-31T18:02",
    "duration_h": 0,
    "lat": 47.23255,
    "lon": 4.90452
  },
  {
    "city": "Flagey-Echézeaux",
    "start": "2025-06-01T12:10",
    "end": "2025-06-01T12:10",
    "duration_h": 0,
    "lat": 47.14228,
    "lon": 4.94511
  },
  {
    "city": "Formigny La Bataille",
    "start": "2025-05-02T16:07",
    "end": "2025-05-02T16:07",
    "duration_h": 0,
    "lat": 49.34439,
    "lon": -1.09021
  },
  {
    "city": "Grandcamp-Maisy",
    "start": "2025-05-02T16:48",
    "end": "2025-05-02T16:48",
    "duration_h": 0,
    "lat": 49.34439,
    "lon": -1.09021
  },
  {
    "city": "Granville",
    "start": "2025-05-04T18:16",
    "end": "2025-05-04T18:16",
    "duration_h": 0,
    "lat": 48.83991,
    "lon": 2.31941
  },
  {
    "city": "Grignon",
    "start": "2025-05-30T12:48",
    "end": "2025-05-30T12:48",
    "duration_h": 0,
    "lat": 47.54099,
    "lon": 4.43879
  },
  {
    "city": "Isigny-sur-Mer",
    "start": "2025-05-03T20:28",
    "end": "2025-05-03T20:33",
    "duration_h": 0,
    "lat": 49.10607,
    "lon": -1.60749
  },
  {
    "city": "Lion-sur-Mer",
    "start": "2025-05-01T17:16",
    "end": "2025-05-01T17:34",
    "duration_h": 0,
    "lat": 48.8761,
    "lon": 2.32496
  },
  {
    "city": "Maconge",
    "start": "2025-05-31T10:55",
    "end": "2025-05-31T10:55",
    "duration_h": 0,
    "lat": 47.18233,
    "lon": 4.68668
  },
  {
    "city": "Meursault",
    "start": "2025-06-01T17:07",
    "end": "2025-06-01T17:07",
    "duration_h": 0,
    "lat": 46.90749,
    "lon": 4.74978
  },
  {
    "city": "Montbard",
    "start": "2025-05-29T23:17",
    "end": "2025-07-17T18:10",
    "duration_h": 1171,
    "lat": 47.56529,
    "lon": 4.36939
  },
  {
    "city": "Osmanville",
    "start": "2025-05-02T19:48",
    "end": "2025-05-02T20:13",
    "duration_h": 0,
    "lat": 49.34439,
    "lon": -1.09021
  },
  {
    "city": "Pommard",
    "start": "2025-06-01T16:43",
    "end": "2025-06-01T16:43",
    "duration_h": 0,
    "lat": 46.90749,
    "lon": 4.74978
  },
  {
    "city": "Port-en-Bessin-Huppain",
    "start": "2025-05-02T12:23",
    "end": "2025-05-02T15:59",
    "duration_h": 4,
    "lat": 49.34906,
    "lon": -0.90312
  },
  {
    "city": "Pouillenay",
    "start": "2025-05-30T13:21",
    "end": "2025-05-30T13:21",
    "duration_h": 0,
    "lat": 47.47488,
    "lon": 4.45669
  },
  {
    "city": "Pouilly-en-Auxois",
    "start": "2025-05-30T20:25",
    "end": "2025-05-30T20:45",
    "duration_h": 0,
    "lat": 47.26479,
    "lon": 4.54991
  },
  {
    "city": "Premeaux-Prissey",
    "start": "2025-06-01T12:46",
    "end": "2025-06-01T12:46",
    "duration_h": 0,
    "lat": 47.07875,
    "lon": 4.89659
  },
  {
    "city": "Ravières",
    "start": "2025-05-29T19:03",
    "end": "2025-05-29T19:03",
    "duration_h": 0,
    "lat": 47.64024,
    "lon": 4.29524
  },
  {
    "city": "Remigny",
    "start": "2025-06-01T17:43",
    "end": "2025-06-01T17:43",
    "duration_h": 0,
    "lat": 46.90749,
    "lon": 4.74978
  },
  {
    "city": "Santenay",
    "start": "2025-06-01T17:42",
    "end": "2025-06-01T17:47",
    "duration_h": 0,
    "lat": 46.90749,
    "lon": 4.74978
  },
  {
    "city": "Tonnerre",
    "start": "2025-05-29T15:31",
    "end": "2025-05-29T16:15",
    "duration_h": 1,
    "lat": 47.85894,
    "lon": 3.99219
  },
  {
    "city": "Vandenesse-en-Auxois",
    "start": "2025-05-31T11:03",
    "end": "2025-05-31T11:03",
    "duration_h": 0,
    "lat": 47.16714,
    "lon": 4.70256
  },
  {
    "city": "Velars-sur-Ouche",
    "start": "2025-05-31T13:06",
    "end": "2025-05-31T13:06",
    "duration_h": 0,
    "lat": 47.33287,
    "lon": 4.97954
  },
  {
    "city": "Vosne-Romanée",
    "start": "2025-06-01T12:18",
    "end": "2025-06-01T12:18",
    "duration_h": 0,
    "lat": 47.12623,
    "lon": 4.94166
  },
  {
    "city": "Aisy-sur-Armançon",
    "start": "2025-05-29T19:29",
    "end": "2025-05-29T19:29",
    "duration_h": 0,
    "lat": 47.63107,
    "lon": 4.33135
  },
  {
    "city": "Arromanches-les-Bains",
    "start": "2025-05-01T20:05",
    "end": "2025-05-01T20:13",
    "duration_h": 0,
    "lat": 48.8761,
    "lon": 2.32496
  },
  {
    "city": "Aure_sur_Mer",
    "start": "2025-05-02T12:48",
    "end": "2025-05-02T12:52",
    "duration_h": 0,
    "lat": 49.36605,
    "lon": -0.86795
  },
  {
    "city": "Bellecombe-en-Bauges",
    "start": "2025-07-16T13:03",
    "end": "2025-07-16T13:03",
    "duration_h": 0,
    "lat": 46.90749,
    "lon": 4.74978
  },
  {
    "city": "Bonneville",
    "start": "2025-07-19T13:22",
    "end": "2025-07-19T13:22",
    "duration_h": 0,
    "lat": 46.90749,
    "lon": 4.74978
  },
  {
    "city": "Bourges",
    "start": "2025-11-10T11:55",
    "end": "2025-11-10T13:25",
    "duration_h": 2,
    "lat": 46.90749,
    "lon": 4.74978
  },
  {
    "city": "Caen",
    "start": "2025-05-01T15:05",
    "end": "2025-05-01T15:05",
    "duration_h": 0,
    "lat": 48.8761,
    "lon": 2.32496
  },
  {
    "city": "Carentan-les-Marais",
    "start": "2025-05-03T14:03",
    "end": "2025-07-17T18:11",
    "duration_h": 1804,
    "lat": 48.55643,
    "lon": -0.01817
  },
  {
    "city": "Chagny",
    "start": "2025-06-01T18:23",
    "end": "2025-06-01T18:23",
    "duration_h": 0,
    "lat": 46.90749,
    "lon": 4.74978
  },
  {
    "city": "Chambéry",
    "start": "2025-07-15T21:49",
    "end": "2025-07-15T21:50",
    "duration_h": 0,
    "lat": 46.90749,
    "lon": 4.74978
  },
  {
    "city": "Chevilly-Larue",
    "start": "2025-05-29T11:24",
    "end": "2026-02-08T22:27",
    "duration_h": 6131,
    "lat": 47.00268,
    "lon": 4.67213
  },
  {
    "city": "Colleville-sur-Mer",
    "start": "2025-05-02T16:08",
    "end": "2025-05-02T16:08",
    "duration_h": 0,
    "lat": 49.34439,
    "lon": -1.09021
  },
  {
    "city": "Courseulles-sur-Mer",
    "start": "2025-05-01T18:37",
    "end": "2025-05-01T18:37",
    "duration_h": 0,
    "lat": 48.8761,
    "lon": 2.32496
  },
  {
    "city": "Donville-les-Bains",
    "start": "2025-05-04T18:16",
    "end": "2025-05-04T18:17",
    "duration_h": 0,
    "lat": 48.83991,
    "lon": 2.31941
  },
  {
    "city": "Doussard",
    "start": "2025-07-16T14:54",
    "end": "2025-07-16T14:54",
    "duration_h": 0,
    "lat": 46.90749,
    "lon": 4.74978
  },
  {
    "city": "Entrevernes",
    "start": "2025-07-16T14:31",
    "end": "2025-07-16T14:55",
    "duration_h": 0,
    "lat": 46.90749,
    "lon": 4.74978
  },
  {
    "city": "Faverges-Seythenex",
    "start": "2025-07-17T18:23",
    "end": "2025-07-17T18:39",
    "duration_h": 0,
    "lat": 46.90749,
    "lon": 4.74978
  },
  {
    "city": "Gazeran",
    "start": "2025-10-24T15:54",
    "end": "2025-10-24T15:54",
    "duration_h": 0,
    "lat": 46.90749,
    "lon": 4.74978
  },
  {
    "city": "Gevrey-Chambertin",
    "start": "2025-05-31T18:55",
    "end": "2025-05-31T19:10",
    "duration_h": 0,
    "lat": 47.23255,
    "lon": 4.90452
  },
  {
    "city": "Gouville-sur-Mer",
    "start": "2025-05-03T20:49",
    "end": "2025-05-04T11:53",
    "duration_h": 15,
    "lat": 49.05284,
    "lon": -0.82211
  },
  {
    "city": "Huppain",
    "start": "2025-05-02T11:34",
    "end": "2025-05-02T12:28",
    "duration_h": 1,
    "lat": 49.34357,
    "lon": -0.80079
  },
  {
    "city": "Ivry-sur-Seine",
    "start": "2025-06-22T22:19",
    "end": "2025-06-22T22:19",
    "duration_h": 0,
    "lat": 46.90749,
    "lon": 4.74978
  },
  {
    "city": "La_Compôte",
    "start": "2025-07-17T22:13",
    "end": "2025-07-17T22:26",
    "duration_h": 0,
    "lat": 46.90749,
    "lon": 4.74978
  },
  {
    "city": "La_Roche-sur-Foron",
    "start": "2025-07-19T13:31",
    "end": "2025-07-19T13:31",
    "duration_h": 0,
    "lat": 46.90749,
    "lon": 4.74978
  },
  {
    "city": "Lathuile",
    "start": "2025-07-16T13:14",
    "end": "2025-07-16T13:15",
    "duration_h": 0,
    "lat": 46.90749,
    "lon": 4.74978
  },
  {
    "city": "Les_Déserts",
    "start": "2025-07-15T17:39",
    "end": "2025-07-15T19:18",
    "duration_h": 2,
    "lat": 46.90749,
    "lon": 4.74978
  },
  {
    "city": "Les_Veys",
    "start": "2025-05-03T13:31",
    "end": "2025-05-03T13:31",
    "duration_h": 0,
    "lat": 49.14485,
    "lon": -1.56839
  },
  {
    "city": "Lézinnes",
    "start": "2025-05-29T16:56",
    "end": "2025-05-29T16:56",
    "duration_h": 0,
    "lat": 47.81133,
    "lon": 4.11981
  },
  {
    "city": "Louvières",
    "start": "2025-05-02T16:07",
    "end": "2025-05-02T16:08",
    "duration_h": 0,
    "lat": 49.34439,
    "lon": -1.09021
  },
  {
    "city": "Mondeville",
    "start": "2025-05-01T15:59",
    "end": "2025-05-01T15:59",
    "duration_h": 0,
    "lat": 48.8761,
    "lon": 2.32496
  },
  {
    "city": "Nançay",
    "start": "2025-11-11T13:20",
    "end": "2025-11-11T13:51",
    "duration_h": 1,
    "lat": 46.90749,
    "lon": 4.74978
  },
  {
    "city": "Neuvy-sur-Barangeon",
    "start": "2025-11-11T13:19",
    "end": "2025-11-11T13:19",
    "duration_h": 0,
    "lat": 46.90749,
    "lon": 4.74978
  },
  {
    "city": "Nuits-Saint-Georges",
    "start": "2025-06-01T12:33",
    "end": "2025-06-01T12:33",
    "duration_h": 0,
    "lat": 47.10311,
    "lon": 4.92172
  },
  {
    "city": "Orval",
    "start": "2025-05-04T14:12",
    "end": "2025-05-04T14:17",
    "duration_h": 0,
    "lat": 48.83991,
    "lon": 2.31941
  },
  {
    "city": "Ouistreham",
    "start": "2025-05-01T16:55",
    "end": "2025-05-01T16:55",
    "duration_h": 0,
    "lat": 48.8761,
    "lon": 2.32496
  },
  {
    "city": "Paris",
    "start": "2026-02-17T20:21",
    "end": "2026-03-04T16:41",
    "duration_h": 356,
    "lat": 46.90749,
    "lon": 4.74978
  },
  {
    "city": "Perrigny-sur-Armançon",
    "start": "2025-05-29T19:14",
    "end": "2025-05-29T19:14",
    "duration_h": 0,
    "lat": 47.62418,
    "lon": 4.32805
  },
  {
    "city": "Premeaux",
    "start": "2025-06-01T12:49",
    "end": "2025-06-01T12:49",
    "duration_h": 0,
    "lat": 47.07647,
    "lon": 4.88917
  },
  {
    "city": "Rambouillet",
    "start": "2025-10-24T14:30",
    "end": "2025-10-24T15:02",
    "duration_h": 1,
    "lat": 46.90749,
    "lon": 4.74978
  },
  {
    "city": "Regnéville-sur-Mer",
    "start": "2025-05-04T14:37",
    "end": "2025-05-04T14:50",
    "duration_h": 0,
    "lat": 48.83991,
    "lon": 2.31941
  },
  {
    "city": "Reims",
    "start": "2025-06-14T18:35",
    "end": "2025-06-14T19:07",
    "duration_h": 1,
    "lat": 46.90749,
    "lon": 4.74978
  },
  {
    "city": "Rougemont",
    "start": "2025-05-29T19:29",
    "end": "2025-05-29T19:29",
    "duration_h": 0,
    "lat": 47.63107,
    "lon": 4.33135
  },
  {
    "city": "Saint-Laurent",
    "start": "2025-07-19T12:51",
    "end": "2026-02-04T22:54",
    "duration_h": 4810,
    "lat": 46.90749,
    "lon": 4.74978
  },
  {
    "city": "Saint-Laurent-sur-Mer",
    "start": "2025-05-02T13:55",
    "end": "2025-07-19T16:00",
    "duration_h": 1874,
    "lat": 48.96462,
    "lon": -0.10962
  },
  {
    "city": "Saint-Martin_de_Bréhal",
    "start": "2025-05-04T15:56",
    "end": "2025-05-04T15:56",
    "duration_h": 0,
    "lat": 48.83991,
    "lon": 2.31941
  },
  {
    "city": "Saint-Sixt",
    "start": "2025-07-19T12:29",
    "end": "2025-11-30T16:29",
    "duration_h": 3220,
    "lat": 46.90749,
    "lon": 4.74978
  },
  {
    "city": "Sceaux",
    "start": "2026-01-25T14:21",
    "end": "2026-01-25T14:21",
    "duration_h": 0,
    "lat": 46.90749,
    "lon": 4.74978
  },
  {
    "city": "Sully-sur-Loire",
    "start": "2025-11-11T15:05",
    "end": "2025-11-11T15:05",
    "duration_h": 0,
    "lat": 46.90749,
    "lon": 4.74978
  },
  {
    "city": "Talant",
    "start": "2025-05-31T13:38",
    "end": "2025-05-31T13:38",
    "duration_h": 0,
    "lat": 47.29653,
    "lon": 5.01632
  },
  {
    "city": "Thorey-sur-Ouche",
    "start": "2025-05-31T11:37",
    "end": "2025-05-31T11:38",
    "duration_h": 0,
    "lat": 47.2366,
    "lon": 4.74832
  },
  {
    "city": "unknown",
    "start": "2025-07-15T17:26",
    "end": "2025-07-15T19:23",
    "duration_h": 2,
    "lat": 46.90749,
    "lon": 4.74978
  },
  {
    "city": "Ver-sur-Mer",
    "start": "2025-05-01T19:04",
    "end": "2025-05-01T19:19",
    "duration_h": 0,
    "lat": 48.8761,
    "lon": 2.32496
  },
  {
    "city": "Vierville-sur-Mer",
    "start": "2025-05-02T15:58",
    "end": "2025-05-02T15:58",
    "duration_h": 0,
    "lat": 49.34439,
    "lon": -1.09021
  },
  {
    "city": "Vitry-sur-Seine",
    "start": "2025-05-01T16:55",
    "end": "2026-02-22T23:25",
    "duration_h": 7134,
    "lat": 46.99599,
    "lon": 4.65277
  },
  {
    "city": "Vougeot",
    "start": "2025-06-01T12:08",
    "end": "2025-06-01T12:10",
    "duration_h": 0,
    "lat": 47.14407,
    "lon": 4.94528
  }
]